SlyYTDAPI/__init__.py
SlyYTDAPI/__main__.py
SlyYTDAPI/livechat.py
SlyYTDAPI/members.py
SlyYTDAPI/ytdapi.py
SlyYTDAPI-0.4.12.dist-info/LICENSE
SlyYTDAPI-0.4.12.dist-info/METADATA
SlyYTDAPI-0.4.12.dist-info/WHEEL
SlyYTDAPI-0.4.12.dist-info/top_level.txt
SlyYTDAPI-0.4.12.dist-info/RECORD
