Metadata-Version: 2.1
Name: SlyYTDAPI
Version: 0.4.12
Summary: No-boilerplate, async and typed YouTube Data API access.
Author: Dunkyl 🔣🔣
License: The MIT License
Project-URL: Homepage, https://docs.dunkyl.net/SlyYTDAPI-Python/
Project-URL: Repository, https://github.com/dunkyl/SlyYTDAPI-Python
Project-URL: Documentation, https://docs.dunkyl.net/SlyYTDAPI-Python/
Project-URL: Bug Tracker, https://github.com/dunkyl/SlyYTDAPI-Python/issues
Requires-Python: >=3.10
License-File: LICENSE
Requires-Dist: SlyAPI>=0.5.0
Requires-Dist: SlySerialize
Provides-Extra: dev
Requires-Dist: pytest; extra == "dev"
Requires-Dist: pytest-asyncio; extra == "dev"
Requires-Dist: myst-parser; extra == "dev"
Requires-Dist: furo; extra == "dev"
Requires-Dist: sphinxcontrib-trio; extra == "dev"
Requires-Dist: sphinx-copybutton; extra == "dev"
Requires-Dist: sphinxext-opengraph; extra == "dev"
